bioarticlepusher-1.1.0.dist-info/licenses/LICENSE
pusher/__init__.py
pusher/ai_filter.py
pusher/cli.py
pusher/config_templates.py
pusher/feishu_pusher.py
pusher/search.py
bioarticlepusher-1.1.0.dist-info/METADATA
bioarticlepusher-1.1.0.dist-info/WHEEL
bioarticlepusher-1.1.0.dist-info/entry_points.txt
bioarticlepusher-1.1.0.dist-info/top_level.txt
bioarticlepusher-1.1.0.dist-info/RECORD
