Metadata-Version: 2.4
Name: BioArticlePusher
Version: 1.1.0
Summary: 生物文章推送系统 - 智能搜索、AI过滤和飞书推送
Author: ykongxiang
License-Expression: MIT
Project-URL: Homepage, https://github.com/ykongxiang/BioArticlePusher
Project-URL: Documentation, https://github.com/ykongxiang/BioArticlePusher/blob/main/README.md
Project-URL: Repository, https://github.com/ykongxiang/BioArticlePusher
Project-URL: Issues, https://github.com/ykongxiang/BioArticlePusher/issues
Keywords: bioinformatics,article,search,ai,filter,feishu,pubmed,biorxiv
Classifier: Development Status :: 4 - Beta
Classifier: Intended Audience :: Science/Research
Classifier: Operating System :: OS Independent
Classifier: Programming Language :: Python :: 3
Classifier: Programming Language :: Python :: 3.8
Classifier: Programming Language :: Python :: 3.9
Classifier: Programming Language :: Python :: 3.10
Classifier: Programming Language :: Python :: 3.11
Classifier: Programming Language :: Python :: 3.12
Classifier: Topic :: Scientific/Engineering :: Bio-Informatics
Requires-Python: >=3.8
License-File: LICENSE
Requires-Dist: feedparser>=6.0.0
Requires-Dist: requests>=2.25.0
Requires-Dist: PyYAML>=5.4.0
Requires-Dist: python-dateutil>=2.8.0
Provides-Extra: dev
Requires-Dist: pytest>=7.0.0; extra == "dev"
Requires-Dist: black>=22.0.0; extra == "dev"
Requires-Dist: isort>=5.10.0; extra == "dev"
Requires-Dist: flake8>=4.0.0; extra == "dev"
Dynamic: license-file
